buildpg/__init__.py
buildpg/asyncpg.py
buildpg/clauses.py
buildpg/components.py
buildpg/funcs.py
buildpg/logic.py
buildpg/main.py
buildpg/version.py
buildpg-0.3.dist-info/LICENSE
buildpg-0.3.dist-info/METADATA
buildpg-0.3.dist-info/WHEEL
buildpg-0.3.dist-info/top_level.txt
buildpg-0.3.dist-info/zip-safe
buildpg-0.3.dist-info/RECORD
